gemini_2_0_api/__init__.py
gemini_2_0_api/config.py
gemini_2_0_api/functions.py
gemini_2_0_api/main.py
gemini_2_0_api/models.py
gemini_2_0_api/py.typed
gemini_2_0_api/tuning.py
gemini_2_0_api/types.py
gemini_2_0_api/wrapper.py
gemini_2_0_api-0.1.0.dist-info/LICENSE
gemini_2_0_api-0.1.0.dist-info/METADATA
gemini_2_0_api-0.1.0.dist-info/WHEEL
gemini_2_0_api-0.1.0.dist-info/RECORD
