Metadata-Version: 2.3
Name: gemini-2.0-api
Version: 0.1.0
Summary: A user-friendly wrapper for the Google Gemini 2.0 API
License: MIT
Keywords: gemini,api,wrapper,ai,google,generative ai,llm
Author: Your Name
Author-email: your.email@example.com
Requires-Python: >=3.9,<4.0
Classifier: Development Status :: 4 - Beta
Classifier: Intended Audience :: Developers
Classifier: License :: OSI Approved :: MIT License
Classifier: Programming Language :: Python :: 3
Classifier: Programming Language :: Python :: 3.9
Classifier: Programming Language :: Python :: 3.10
Classifier: Programming Language :: Python :: 3.11
Classifier: Programming Language :: Python :: 3.12
Classifier: Programming Language :: Python :: 3.13
Classifier: Topic :: Scientific/Engineering :: Artificial Intelligence
Classifier: Topic :: Software Development :: Libraries :: Python Modules
Requires-Dist: google-genai (>=1.0.0)
Requires-Dist: pillow (>=10.0.0)
Requires-Dist: pydantic (>=2.0.0,<3.0.0)
Requires-Dist: python-dotenv (>=1.0.0,<2.0.0)
Requires-Dist: requests (>=2.31.0,<3.0.0)
Project-URL: Documentation, https://github.com/yourusername/gemini-2.0-api#readme
Project-URL: Homepage, https://github.com/yourusername/gemini-2.0-api
Project-URL: Repository, https://github.com/yourusername/gemini-2.0-api
